djabberd/__init__.py
djabberd/handlers.py
djabberd/urls.py
djabberd/views.py
djabberd-0.9.6.dist-info/DESCRIPTION.rst
djabberd-0.9.6.dist-info/LICENSE.txt
djabberd-0.9.6.dist-info/METADATA
djabberd-0.9.6.dist-info/RECORD
djabberd-0.9.6.dist-info/WHEEL
djabberd-0.9.6.dist-info/metadata.json
djabberd-0.9.6.dist-info/top_level.txt
tests/__init__.py
tests/handlers.py
tests/settings.py
tests/test_handlers.py
tests/test_views.py
tests/urls.py
