Metadata-Version: 2.0
Name: djabberd
Version: 0.9.6
Summary: Generic application to handle https://ejabberd-saas.com/ Remote Data API calls
Home-page: https://github.com/alej0varas/djabberd
Author: Alexandre Varas
Author-email: alej0varas@gmail.com
License: GPL v3
Platform: UNKNOWN
Classifier: Development Status :: 4 - Beta
Classifier: Environment :: Web Environment
Classifier: Framework :: Django
Classifier: Framework :: Django :: 1.10
Classifier: Framework :: Django :: 1.8
Classifier: Framework :: Django :: 1.9
Classifier: Intended Audience :: Developers
Classifier: License :: OSI Approved :: GNU General Public License v3 or later (GPLv3+)
Classifier: Operating System :: OS Independent
Classifier: Programming Language :: Python
Classifier: Programming Language :: Python :: 3
Classifier: Topic :: Internet :: WWW/HTTP
Classifier: Topic :: Internet :: WWW/HTTP :: Dynamic Content
Requires-Dist: Django (>=1.8,<2)
Requires-Dist: djangorestframework (<4,>=3.2)
